pymagic/__init__.py
pymagic/_base.py
pymagic/decorator_utils.py
pymagic/logger_utils.py
pymagic/tools_utils.py
tests/__init__.py
tests/test_base.py
tests/test_logger_utils.py
tests/test_tools_utils.py
pymagic_guyue-0.0.1.dist-info/LICENSE
pymagic_guyue-0.0.1.dist-info/METADATA
pymagic_guyue-0.0.1.dist-info/WHEEL
pymagic_guyue-0.0.1.dist-info/top_level.txt
pymagic_guyue-0.0.1.dist-info/RECORD
