Metadata-Version: 2.1
Name: pymagic-guyue
Version: 0.0.1
Summary: A utility library for Python development
Home-page: https://github.com/guyue55/pymagic
Author: Guyue
Author-email: guyuecw@qq.com
Classifier: Programming Language :: Python :: 3
Classifier: License :: OSI Approved :: MIT License
Classifier: Operating System :: OS Independent
Requires-Python: >=3.6
License-File: LICENSE
Requires-Dist: loguru
